snapshottest_ext/dataframe.py
snapshottest_ext-0.8.0.dist-info/METADATA
snapshottest_ext-0.8.0.dist-info/WHEEL
snapshottest_ext-0.8.0.dist-info/top_level.txt
snapshottest_ext-0.8.0.dist-info/RECORD
