Metadata-Version: 2.1
Name: snapshottest_ext
Version: 0.8.0
Summary: extra formatter for snapshottest
Home-page: https://github.com/swuecho/snapshottest_ext
Author: Hao Wu
Author-email: echowuaho@foxmail.com
License: MIT
Classifier: License :: OSI Approved :: MIT License
Classifier: Programming Language :: Python :: 3
Classifier: Programming Language :: Python :: 3.7
Requires-Dist: snapshottest
Requires-Dist: pandas
Requires-Dist: pyarrow
